jsonrpc/dispatcher.py
jsonrpc/base.py
jsonrpc/errors.py
jsonrpc/exceptions.py
jsonrpc/manager.py
jsonrpc/response.py
jsonrpc/request.py
jsonrpc/__init__.py
jsonrpc/utils.py
jsonrpc/tests/__init__.py
jsonrpc/tests/test_dispatcher.py
jsonrpc/tests/test_examples.py
jsonrpc/tests/test_jsonrpc.py
jsonrpc/tests/test_jsonrpc_errors.py
jsonrpc/tests/test_utils.py
jsonrpc/tests/test_manager.py
jsonrpc/tests/test_datetime.py
examples/__init__.py
examples/simple/__init__.py
examples/simple/api.py
examples/simple/server.py
examples/simple/client.py
json_rpc_3-1.8.4.dist-info/top_level.txt
json_rpc_3-1.8.4.dist-info/METADATA
json_rpc_3-1.8.4.dist-info/DESCRIPTION.rst
json_rpc_3-1.8.4.dist-info/metadata.json
json_rpc_3-1.8.4.dist-info/WHEEL
json_rpc_3-1.8.4.dist-info/RECORD
