Metadata-Version: 1.1
Name: json-rpc-3
Version: 1.8.4
Summary: Pure Python 3 JSON-RPC 2.0 transport realisation
Home-page: https://github.com/Orhideous/json-rpc
Author: Orhideous
Author-email: orhideous@gmail.com
License: MIT
Keywords: json,rpc,json-rpc,transport
Platform: UNKNOWN
Classifier: Development Status :: 5 - Production/Stable
Classifier: Environment :: Console
Classifier: License :: OSI Approved :: MIT License
Classifier: Natural Language :: English
Classifier: Operating System :: OS Independent
Classifier: Programming Language :: Python :: 3
Classifier: Programming Language :: Python :: 3.2
Classifier: Programming Language :: Python :: 3.3
Classifier: Programming Language :: Python :: 3.4
Classifier: Topic :: Software Development :: Libraries :: Python Modules
